README.md
setup.py
redissimple/__init__.py
redissimple/exception.py
redissimple/rediswrapper.py
redissimple/response_codes.py
redissimple.egg-info/PKG-INFO
redissimple.egg-info/SOURCES.txt
redissimple.egg-info/dependency_links.txt
redissimple.egg-info/requires.txt
redissimple.egg-info/top_level.txt
test/test.py