Metadata-Version: 2.1
Name: redissimple
Version: 0.8
Summary: A library to use Redis Package
Home-page: https://github.com/vcjain/redis-simple
Author: Vikash Jain
Author-email: vikash.jain@galaxyweblinks.co.in
License: MIT
Project-URL: Bug Tracker, https://github.com/vcjain/redis-simple/issues
Platform: UNKNOWN
